markmini-0.5.2.dist-info/METADATA
markmini-0.5.2.dist-info/WHEEL
markmini_py/__init__.py
markmini_py/__init__.pyi
markmini_py/py.typed
markmini_py/markmini_py.cpython-312-darwin.so
markmini-0.5.2.dist-info/RECORD
