Metadata-Version: 2.4
Name: markmini
Version: 0.5.2
Classifier: Programming Language :: Rust
Classifier: Programming Language :: Python :: Implementation :: CPython
Classifier: Programming Language :: Python :: Implementation :: PyPy
License: MIT
Requires-Python: >=3.10
